client/__init__.py
client/client_1.py
client/encryption.py
client/services/__init__.py
client/services/actions.py
client/services/status_code.py
client/test/__init__.py
client/test/test_client.py
gb_mess_client-0.1.0.data/scripts/client_run
gb_mess_client-0.1.0.dist-info/METADATA
gb_mess_client-0.1.0.dist-info/WHEEL
gb_mess_client-0.1.0.dist-info/top_level.txt
gb_mess_client-0.1.0.dist-info/RECORD
